LICENSE
README.md
setup.py
FakeAgent/__init__.py
FakeAgent/agent.py
FakeAgent/types.py
FakeAgent/utils.py
FakeAgent/data/Chrome.json
FakeAgent/data/Edge.json
FakeAgent/data/Firefox.json
FakeAgent/data/InternetExplorer.json
FakeAgent/data/Opera.json
FakeAgent/data/Safari.json
fake_agent.egg-info/PKG-INFO
fake_agent.egg-info/SOURCES.txt
fake_agent.egg-info/dependency_links.txt
fake_agent.egg-info/top_level.txt
scrapers/__init__.py
scrapers/beamtic.py
scrapers/file_utils.py
scrapers/userstring.py