Metadata-Version: 2.1
Name: fake-agent
Version: 0.1.3
Summary: Generate fake user agents on the fly
Home-page: https://github.com/Itz-fork/Fake-agent
Download-URL: https://github.com/Itz-fork/Fake-agent/releases/tag/fake-agent-v0.1.3
Author: Itz-fork
Author-email: itz-fork@users.noreply.github.com
License: MIT
Keywords: user-agent,fake-user-agent,user agent generator
Platform: UNKNOWN
Classifier: Development Status :: 5 - Production/Stable
Classifier: Intended Audience :: Developers
Classifier: Topic :: Education
Classifier: License :: OSI Approved :: MIT License
Classifier: Programming Language :: Python :: 3.6
Classifier: Programming Language :: Python :: 3.9
Classifier: Programming Language :: Python :: 3.10
License-File: LICENSE
